{
  "schemaVersion": "1.0.0",
  "targetPage": "crypto-dashboard Dogfooding",
  "components": [
    {
      "type": "FRAME",
      "name": "CryptoDashboardPage",
      "size": {
        "x": 720,
        "y": 545.5999999999999
      },
      "opacity": 1,
      "visible": true,
      "children": [
        {
          "type": "FRAME",
          "name": "Header",
          "size": {
            "x": 720,
            "y": 62
          },
          "opacity": 1,
          "visible": true,
          "children": [
            {
              "type": "TEXT",
              "name": "CryptoFolio",
              "size": {
                "x": 113.83000183105469,
                "y": 24
              },
              "opacity": 1,
              "visible": true,
              "children": [],
              "fills": [
                {
                  "type": "SOLID",
                  "color": {
                    "r": 0.13333333333333333,
                    "g": 0.7725490196078432,
                    "b": 0.3686274509803922,
                    "a": 1
                  },
                  "opacity": 1
                }
              ],
              "characters": "CryptoFolio",
              "fontSize": 20,
              "fontFamily": "Inter",
              "textAlignHorizontal": "LEFT",
              "fontWeight": 800,
              "fontStyle": "Regular"
            },
            {
              "type": "FRAME",
              "name": "HeaderRight",
              "size": {
                "x": 156.72999954223633,
                "y": 30
              },
              "opacity": 1,
              "visible": true,
              "children": [
                {
                  "type": "TEXT",
                  "name": "Portfolio",
                  "size": {
                    "x": 53.18000030517578,
                    "y": 15.6
                  },
                  "opacity": 1,
                  "visible": true,
                  "children": [],
                  "fills": [
                    {
                      "type": "SOLID",
                      "color": {
                        "r": 1,
                        "g": 1,
                        "b": 1,
                        "a": 1
                      },
                      "opacity": 1
                    }
                  ],
                  "characters": "Portfolio",
                  "fontSize": 13,
                  "fontFamily": "Inter",
                  "textAlignHorizontal": "LEFT",
                  "fontWeight": 600,
                  "fontStyle": "Semi Bold"
                },
                {
                  "type": "TEXT",
                  "name": "Markets",
                  "size": {
                    "x": 49.54999923706055,
                    "y": 15.6
                  },
                  "opacity": 1,
                  "visible": true,
                  "children": [],
                  "fills": [
                    {
                      "type": "SOLID",
                      "color": {
                        "r": 0.44313725490196076,
                        "g": 0.44313725490196076,
                        "b": 0.47843137254901963,
                        "a": 1
                      },
                      "opacity": 1
                    }
                  ],
                  "characters": "Markets",
                  "fontSize": 13,
                  "fontFamily": "Inter",
                  "textAlignHorizontal": "LEFT",
                  "fontWeight": 400,
                  "fontStyle": "Regular"
                },
                {
                  "type": "ELLIPSE",
                  "name": "Avatar",
                  "size": {
                    "x": 30,
                    "y": 30
                  },
                  "opacity": 1,
                  "visible": true,
                  "children": [],
                  "fills": [
                    {
                      "type": "GRADIENT_LINEAR",
                      "opacity": 1,
                      "gradientStops": [
                        {
                          "color": {
                            "r": 0.13333333333333333,
                            "g": 0.7725490196078432,
                            "b": 0.3686274509803922,
                            "a": 1
                          },
                          "position": 0
                        },
                        {
                          "color": {
                            "r": 0.08627450980392157,
                            "g": 0.6392156862745098,
                            "b": 0.2901960784313726,
                            "a": 1
                          },
                          "position": 1
                        }
                      ],
                      "gradientTransform": [
                        [
                          -0.7071067811865475,
                          0.7071067811865476,
                          0.49999999999999994
                        ],
                        [
                          -0.7071067811865476,
                          -0.7071067811865475,
                          1.2071067811865475
                        ]
                      ]
                    }
                  ]
                }
              ],
              "stackMode": "HORIZONTAL",
              "itemSpacing": 12,
              "paddingTop": 0,
              "paddingRight": 0,
              "paddingBottom": 0,
              "paddingLeft": 0,
              "primaryAxisAlignItems": "MIN",
              "counterAxisAlignItems": "CENTER"
            }
          ],
          "fills": [
            {
              "type": "SOLID",
              "color": {
                "r": 0.0784313725490196,
                "g": 0.0784313725490196,
                "b": 0.0784313725490196,
                "a": 1
              },
              "opacity": 1
            }
          ],
          "stackMode": "HORIZONTAL",
          "itemSpacing": 0,
          "paddingTop": 16,
          "paddingRight": 24,
          "paddingBottom": 16,
          "paddingLeft": 24,
          "primaryAxisAlignItems": "SPACE_BETWEEN",
          "counterAxisAlignItems": "CENTER",
          "layoutSizingHorizontal": "FILL"
        },
        {
          "type": "FRAME",
          "name": "PortfolioCard",
          "size": {
            "x": 720,
            "y": 165.2
          },
          "opacity": 1,
          "visible": true,
          "children": [
            {
              "type": "TEXT",
              "name": "Total Portfolio Value",
              "size": {
                "x": 124.30999755859375,
                "y": 15.6
              },
              "opacity": 1,
              "visible": true,
              "children": [],
              "fills": [
                {
                  "type": "SOLID",
                  "color": {
                    "r": 0.5254901960784314,
                    "g": 0.9372549019607843,
                    "b": 0.6745098039215687,
                    "a": 1
                  },
                  "opacity": 1
                }
              ],
              "characters": "Total Portfolio Value",
              "fontSize": 13,
              "fontFamily": "Inter",
              "textAlignHorizontal": "LEFT",
              "fontWeight": 500,
              "fontStyle": "Medium"
            },
            {
              "type": "TEXT",
              "name": "$47,832.54",
              "size": {
                "x": 225.82000732421875,
                "y": 48
              },
              "opacity": 1,
              "visible": true,
              "children": [],
              "fills": [
                {
                  "type": "SOLID",
                  "color": {
                    "r": 1,
                    "g": 1,
                    "b": 1,
                    "a": 1
                  },
                  "opacity": 1
                }
              ],
              "characters": "$47,832.54",
              "fontSize": 40,
              "fontFamily": "Inter",
              "textAlignHorizontal": "LEFT",
              "fontWeight": 800,
              "fontStyle": "Regular"
            },
            {
              "type": "FRAME",
              "name": "ChangeRow",
              "size": {
                "x": 179.27000427246094,
                "y": 21.6
              },
              "opacity": 1,
              "visible": true,
              "children": [
                {
                  "type": "FRAME",
                  "name": "ChangeBadge",
                  "size": {
                    "x": 66.22000122070312,
                    "y": 21.6
                  },
                  "opacity": 1,
                  "visible": true,
                  "children": [
                    {
                      "type": "TEXT",
                      "name": "+4.32%",
                      "size": {
                        "x": 50.220001220703125,
                        "y": 15.6
                      },
                      "opacity": 1,
                      "visible": true,
                      "children": [],
                      "fills": [
                        {
                          "type": "SOLID",
                          "color": {
                            "r": 0.13333333333333333,
                            "g": 0.7725490196078432,
                            "b": 0.3686274509803922,
                            "a": 1
                          },
                          "opacity": 1
                        }
                      ],
                      "characters": "+4.32%",
                      "fontSize": 13,
                      "fontFamily": "Inter",
                      "textAlignHorizontal": "LEFT",
                      "fontWeight": 600,
                      "fontStyle": "Semi Bold"
                    }
                  ],
                  "fills": [
                    {
                      "type": "SOLID",
                      "color": {
                        "r": 0.13333333333333333,
                        "g": 0.7725490196078432,
                        "b": 0.3686274509803922,
                        "a": 1
                      },
                      "opacity": 0.2
                    }
                  ],
                  "cornerRadius": 6,
                  "stackMode": "HORIZONTAL",
                  "itemSpacing": 0,
                  "paddingTop": 3,
                  "paddingRight": 8,
                  "paddingBottom": 3,
                  "paddingLeft": 8,
                  "primaryAxisAlignItems": "MIN",
                  "counterAxisAlignItems": "MIN"
                },
                {
                  "type": "TEXT",
                  "name": "+$1,982.41 today",
                  "size": {
                    "x": 105.05000305175781,
                    "y": 15.6
                  },
                  "opacity": 1,
                  "visible": true,
                  "children": [],
                  "fills": [
                    {
                      "type": "SOLID",
                      "color": {
                        "r": 0.5254901960784314,
                        "g": 0.9372549019607843,
                        "b": 0.6745098039215687,
                        "a": 1
                      },
                      "opacity": 1
                    }
                  ],
                  "characters": "+$1,982.41 today",
                  "fontSize": 13,
                  "fontFamily": "Inter",
                  "textAlignHorizontal": "LEFT",
                  "fontWeight": 400,
                  "fontStyle": "Regular"
                }
              ],
              "stackMode": "HORIZONTAL",
              "itemSpacing": 8,
              "paddingTop": 0,
              "paddingRight": 0,
              "paddingBottom": 0,
              "paddingLeft": 0,
              "primaryAxisAlignItems": "MIN",
              "counterAxisAlignItems": "CENTER"
            }
          ],
          "fills": [
            {
              "type": "GRADIENT_LINEAR",
              "opacity": 1,
              "gradientStops": [
                {
                  "color": {
                    "r": 0.0784313725490196,
                    "g": 0.3254901960784314,
                    "b": 0.17647058823529413,
                    "a": 1
                  },
                  "position": 0
                },
                {
                  "color": {
                    "r": 0.0196078431372549,
                    "g": 0.1803921568627451,
                    "b": 0.08627450980392157,
                    "a": 1
                  },
                  "position": 1
                }
              ],
              "gradientTransform": [
                [
                  -0.7071067811865475,
                  0.7071067811865476,
                  0.49999999999999994
                ],
                [
                  -0.7071067811865476,
                  -0.7071067811865475,
                  1.2071067811865475
                ]
              ]
            }
          ],
          "stackMode": "VERTICAL",
          "itemSpacing": 12,
          "paddingTop": 28,
          "paddingRight": 24,
          "paddingBottom": 28,
          "paddingLeft": 24,
          "primaryAxisAlignItems": "MIN",
          "counterAxisAlignItems": "MIN",
          "layoutSizingHorizontal": "FILL"
        },
        {
          "type": "FRAME",
          "name": "CoinList",
          "size": {
            "x": 720,
            "y": 318.4
          },
          "opacity": 1,
          "visible": true,
          "children": [
            {
              "type": "FRAME",
              "name": "ListHeader",
              "size": {
                "x": 704,
                "y": 30.4
              },
              "opacity": 1,
              "visible": true,
              "children": [
                {
                  "type": "TEXT",
                  "name": "Asset",
                  "size": {
                    "x": 591.7999992370605,
                    "y": 14.399999999999999
                  },
                  "opacity": 1,
                  "visible": true,
                  "children": [],
                  "fills": [
                    {
                      "type": "SOLID",
                      "color": {
                        "r": 0.3215686274509804,
                        "g": 0.3215686274509804,
                        "b": 0.3568627450980392,
                        "a": 1
                      },
                      "opacity": 1
                    }
                  ],
                  "layoutSizingHorizontal": "FILL",
                  "characters": "Asset",
                  "fontSize": 12,
                  "fontFamily": "Inter",
                  "textAlignHorizontal": "LEFT",
                  "fontWeight": 500,
                  "fontStyle": "Medium"
                },
                {
                  "type": "TEXT",
                  "name": "Price",
                  "size": {
                    "x": 29.43000030517578,
                    "y": 14.399999999999999
                  },
                  "opacity": 1,
                  "visible": true,
                  "children": [],
                  "fills": [
                    {
                      "type": "SOLID",
                      "color": {
                        "r": 0.3215686274509804,
                        "g": 0.3215686274509804,
                        "b": 0.3568627450980392,
                        "a": 1
                      },
                      "opacity": 1
                    }
                  ],
                  "characters": "Price",
                  "fontSize": 12,
                  "fontFamily": "Inter",
                  "textAlignHorizontal": "LEFT",
                  "fontWeight": 500,
                  "fontStyle": "Medium"
                },
                {
                  "type": "TEXT",
                  "name": "Holdings",
                  "size": {
                    "x": 50.77000045776367,
                    "y": 14.399999999999999
                  },
                  "opacity": 1,
                  "visible": true,
                  "children": [],
                  "fills": [
                    {
                      "type": "SOLID",
                      "color": {
                        "r": 0.3215686274509804,
                        "g": 0.3215686274509804,
                        "b": 0.3568627450980392,
                        "a": 1
                      },
                      "opacity": 1
                    }
                  ],
                  "characters": "Holdings",
                  "fontSize": 12,
                  "fontFamily": "Inter",
                  "textAlignHorizontal": "RIGHT",
                  "fontWeight": 500,
                  "fontStyle": "Medium"
                }
              ],
              "stackMode": "HORIZONTAL",
              "itemSpacing": 0,
              "paddingTop": 8,
              "paddingRight": 16,
              "paddingBottom": 8,
              "paddingLeft": 16,
              "primaryAxisAlignItems": "MIN",
              "counterAxisAlignItems": "CENTER",
              "layoutSizingHorizontal": "FILL"
            },
            {
              "type": "FRAME",
              "name": "Coin: Bitcoin",
              "size": {
                "x": 704,
                "y": 64
              },
              "opacity": 1,
              "visible": true,
              "children": [
                {
                  "type": "FRAME",
                  "name": "CoinInfo",
                  "size": {
                    "x": 487.0900001525879,
                    "y": 36
                  },
                  "opacity": 1,
                  "visible": true,
                  "children": [
                    {
                      "type": "ELLIPSE",
                      "name": "Icon:BTC",
                      "size": {
                        "x": 36,
                        "y": 36
                      },
                      "opacity": 1,
                      "visible": true,
                      "children": [],
                      "fills": [
                        {
                          "type": "SOLID",
                          "color": {
                            "r": 0.9686274509803922,
                            "g": 0.5764705882352941,
                            "b": 0.10196078431372549,
                            "a": 1
                          },
                          "opacity": 1
                        }
                      ]
                    },
                    {
                      "type": "FRAME",
                      "name": "CoinName",
                      "size": {
                        "x": 46.61000061035156,
                        "y": 33.2
                      },
                      "opacity": 1,
                      "visible": true,
                      "children": [
                        {
                          "type": "TEXT",
                          "name": "Bitcoin",
                          "size": {
                            "x": 46.61000061035156,
                            "y": 16.8
                          },
                          "opacity": 1,
                          "visible": true,
                          "children": [],
                          "fills": [
                            {
                              "type": "SOLID",
                              "color": {
                                "r": 1,
                                "g": 1,
                                "b": 1,
                                "a": 1
                              },
                              "opacity": 1
                            }
                          ],
                          "characters": "Bitcoin",
                          "fontSize": 14,
                          "fontFamily": "Inter",
                          "textAlignHorizontal": "LEFT",
                          "fontWeight": 600,
                          "fontStyle": "Semi Bold"
                        },
                        {
                          "type": "TEXT",
                          "name": "BTC",
                          "size": {
                            "x": 23.329999923706055,
                            "y": 14.399999999999999
                          },
                          "opacity": 1,
                          "visible": true,
                          "children": [],
                          "fills": [
                            {
                              "type": "SOLID",
                              "color": {
                                "r": 0.44313725490196076,
                                "g": 0.44313725490196076,
                                "b": 0.47843137254901963,
                                "a": 1
                              },
                              "opacity": 1
                            }
                          ],
                          "characters": "BTC",
                          "fontSize": 12,
                          "fontFamily": "Inter",
                          "textAlignHorizontal": "LEFT",
                          "fontWeight": 400,
                          "fontStyle": "Regular"
                        }
                      ],
                      "stackMode": "VERTICAL",
                      "itemSpacing": 2,
                      "paddingTop": 0,
                      "paddingRight": 0,
                      "paddingBottom": 0,
                      "paddingLeft": 0,
                      "primaryAxisAlignItems": "MIN",
                      "counterAxisAlignItems": "MIN"
                    }
                  ],
                  "stackMode": "HORIZONTAL",
                  "itemSpacing": 10,
                  "paddingTop": 0,
                  "paddingRight": 0,
                  "paddingBottom": 0,
                  "paddingLeft": 0,
                  "primaryAxisAlignItems": "MIN",
                  "counterAxisAlignItems": "CENTER",
                  "layoutSizingHorizontal": "FILL"
                },
                {
                  "type": "FRAME",
                  "name": "PriceCol",
                  "size": {
                    "x": 75.06999969482422,
                    "y": 33.2
                  },
                  "opacity": 1,
                  "visible": true,
                  "children": [
                    {
                      "type": "TEXT",
                      "name": "$68,432.10",
                      "size": {
                        "x": 75.06999969482422,
                        "y": 16.8
                      },
                      "opacity": 1,
                      "visible": true,
                      "children": [],
                      "fills": [
                        {
                          "type": "SOLID",
                          "color": {
                            "r": 1,
                            "g": 1,
                            "b": 1,
                            "a": 1
                          },
                          "opacity": 1
                        }
                      ],
                      "characters": "$68,432.10",
                      "fontSize": 14,
                      "fontFamily": "Inter",
                      "textAlignHorizontal": "LEFT",
                      "fontWeight": 500,
                      "fontStyle": "Medium"
                    },
                    {
                      "type": "TEXT",
                      "name": "+3.24%",
                      "size": {
                        "x": 46.52000045776367,
                        "y": 14.399999999999999
                      },
                      "opacity": 1,
                      "visible": true,
                      "children": [],
                      "fills": [
                        {
                          "type": "SOLID",
                          "color": {
                            "r": 0.13333333333333333,
                            "g": 0.7725490196078432,
                            "b": 0.3686274509803922,
                            "a": 1
                          },
                          "opacity": 1
                        }
                      ],
                      "characters": "+3.24%",
                      "fontSize": 12,
                      "fontFamily": "Inter",
                      "textAlignHorizontal": "LEFT",
                      "fontWeight": 600,
                      "fontStyle": "Semi Bold"
                    }
                  ],
                  "stackMode": "VERTICAL",
                  "itemSpacing": 2,
                  "paddingTop": 0,
                  "paddingRight": 0,
                  "paddingBottom": 0,
                  "paddingLeft": 0,
                  "primaryAxisAlignItems": "MIN",
                  "counterAxisAlignItems": "MAX"
                },
                {
                  "type": "FRAME",
                  "name": "HoldingCol",
                  "size": {
                    "x": 109.84000015258789,
                    "y": 33.2
                  },
                  "opacity": 1,
                  "visible": true,
                  "children": [
                    {
                      "type": "TEXT",
                      "name": "0.42 BTC",
                      "size": {
                        "x": 61.84000015258789,
                        "y": 16.8
                      },
                      "opacity": 1,
                      "visible": true,
                      "children": [],
                      "fills": [
                        {
                          "type": "SOLID",
                          "color": {
                            "r": 1,
                            "g": 1,
                            "b": 1,
                            "a": 1
                          },
                          "opacity": 1
                        }
                      ],
                      "characters": "0.42 BTC",
                      "fontSize": 14,
                      "fontFamily": "Inter",
                      "textAlignHorizontal": "LEFT",
                      "fontWeight": 500,
                      "fontStyle": "Medium"
                    },
                    {
                      "type": "TEXT",
                      "name": "$28,741",
                      "size": {
                        "x": 43.95000076293945,
                        "y": 14.399999999999999
                      },
                      "opacity": 1,
                      "visible": true,
                      "children": [],
                      "fills": [
                        {
                          "type": "SOLID",
                          "color": {
                            "r": 0.44313725490196076,
                            "g": 0.44313725490196076,
                            "b": 0.47843137254901963,
                            "a": 1
                          },
                          "opacity": 1
                        }
                      ],
                      "characters": "$28,741",
                      "fontSize": 12,
                      "fontFamily": "Inter",
                      "textAlignHorizontal": "LEFT",
                      "fontWeight": 400,
                      "fontStyle": "Regular"
                    }
                  ],
                  "stackMode": "VERTICAL",
                  "itemSpacing": 2,
                  "paddingTop": 0,
                  "paddingRight": 24,
                  "paddingBottom": 0,
                  "paddingLeft": 24,
                  "primaryAxisAlignItems": "MIN",
                  "counterAxisAlignItems": "MAX"
                }
              ],
              "strokes": [
                {
                  "color": {
                    "r": 1,
                    "g": 1,
                    "b": 1,
                    "a": 0.06
                  },
                  "weight": 1,
                  "align": "INSIDE"
                }
              ],
              "stackMode": "HORIZONTAL",
              "itemSpacing": 0,
              "paddingTop": 14,
              "paddingRight": 16,
              "paddingBottom": 14,
              "paddingLeft": 16,
              "primaryAxisAlignItems": "MIN",
              "counterAxisAlignItems": "CENTER",
              "layoutSizingHorizontal": "FILL"
            },
            {
              "type": "FRAME",
              "name": "Coin: Ethereum",
              "size": {
                "x": 704,
                "y": 64
              },
              "opacity": 1,
              "visible": true,
              "children": [
                {
                  "type": "FRAME",
                  "name": "CoinInfo",
                  "size": {
                    "x": 501.50999450683594,
                    "y": 36
                  },
                  "opacity": 1,
                  "visible": true,
                  "children": [
                    {
                      "type": "ELLIPSE",
                      "name": "Icon:ETH",
                      "size": {
                        "x": 36,
                        "y": 36
                      },
                      "opacity": 1,
                      "visible": true,
                      "children": [],
                      "fills": [
                        {
                          "type": "SOLID",
                          "color": {
                            "r": 0.3843137254901961,
                            "g": 0.49411764705882355,
                            "b": 0.9176470588235294,
                            "a": 1
                          },
                          "opacity": 1
                        }
                      ]
                    },
                    {
                      "type": "FRAME",
                      "name": "CoinName",
                      "size": {
                        "x": 65,
                        "y": 33.2
                      },
                      "opacity": 1,
                      "visible": true,
                      "children": [
                        {
                          "type": "TEXT",
                          "name": "Ethereum",
                          "size": {
                            "x": 65,
                            "y": 16.8
                          },
                          "opacity": 1,
                          "visible": true,
                          "children": [],
                          "fills": [
                            {
                              "type": "SOLID",
                              "color": {
                                "r": 1,
                                "g": 1,
                                "b": 1,
                                "a": 1
                              },
                              "opacity": 1
                            }
                          ],
                          "characters": "Ethereum",
                          "fontSize": 14,
                          "fontFamily": "Inter",
                          "textAlignHorizontal": "LEFT",
                          "fontWeight": 600,
                          "fontStyle": "Semi Bold"
                        },
                        {
                          "type": "TEXT",
                          "name": "ETH",
                          "size": {
                            "x": 23.8799991607666,
                            "y": 14.399999999999999
                          },
                          "opacity": 1,
                          "visible": true,
                          "children": [],
                          "fills": [
                            {
                              "type": "SOLID",
                              "color": {
                                "r": 0.44313725490196076,
                                "g": 0.44313725490196076,
                                "b": 0.47843137254901963,
                                "a": 1
                              },
                              "opacity": 1
                            }
                          ],
                          "characters": "ETH",
                          "fontSize": 12,
                          "fontFamily": "Inter",
                          "textAlignHorizontal": "LEFT",
                          "fontWeight": 400,
                          "fontStyle": "Regular"
                        }
                      ],
                      "stackMode": "VERTICAL",
                      "itemSpacing": 2,
                      "paddingTop": 0,
                      "paddingRight": 0,
                      "paddingBottom": 0,
                      "paddingLeft": 0,
                      "primaryAxisAlignItems": "MIN",
                      "counterAxisAlignItems": "MIN"
                    }
                  ],
                  "stackMode": "HORIZONTAL",
                  "itemSpacing": 10,
                  "paddingTop": 0,
                  "paddingRight": 0,
                  "paddingBottom": 0,
                  "paddingLeft": 0,
                  "primaryAxisAlignItems": "MIN",
                  "counterAxisAlignItems": "CENTER",
                  "layoutSizingHorizontal": "FILL"
                },
                {
                  "type": "FRAME",
                  "name": "PriceCol",
                  "size": {
                    "x": 69.41000366210938,
                    "y": 33.2
                  },
                  "opacity": 1,
                  "visible": true,
                  "children": [
                    {
                      "type": "TEXT",
                      "name": "$3,845.20",
                      "size": {
                        "x": 69.41000366210938,
                        "y": 16.8
                      },
                      "opacity": 1,
                      "visible": true,
                      "children": [],
                      "fills": [
                        {
                          "type": "SOLID",
                          "color": {
                            "r": 1,
                            "g": 1,
                            "b": 1,
                            "a": 1
                          },
                          "opacity": 1
                        }
                      ],
                      "characters": "$3,845.20",
                      "fontSize": 14,
                      "fontFamily": "Inter",
                      "textAlignHorizontal": "LEFT",
                      "fontWeight": 500,
                      "fontStyle": "Medium"
                    },
                    {
                      "type": "TEXT",
                      "name": "+5.67%",
                      "size": {
                        "x": 45.2599983215332,
                        "y": 14.399999999999999
                      },
                      "opacity": 1,
                      "visible": true,
                      "children": [],
                      "fills": [
                        {
                          "type": "SOLID",
                          "color": {
                            "r": 0.13333333333333333,
                            "g": 0.7725490196078432,
                            "b": 0.3686274509803922,
                            "a": 1
                          },
                          "opacity": 1
                        }
                      ],
                      "characters": "+5.67%",
                      "fontSize": 12,
                      "fontFamily": "Inter",
                      "textAlignHorizontal": "LEFT",
                      "fontWeight": 600,
                      "fontStyle": "Semi Bold"
                    }
                  ],
                  "stackMode": "VERTICAL",
                  "itemSpacing": 2,
                  "paddingTop": 0,
                  "paddingRight": 0,
                  "paddingBottom": 0,
                  "paddingLeft": 0,
                  "primaryAxisAlignItems": "MIN",
                  "counterAxisAlignItems": "MAX"
                },
                {
                  "type": "FRAME",
                  "name": "HoldingCol",
                  "size": {
                    "x": 101.08000183105469,
                    "y": 33.2
                  },
                  "opacity": 1,
                  "visible": true,
                  "children": [
                    {
                      "type": "TEXT",
                      "name": "3.2 ETH",
                      "size": {
                        "x": 53.08000183105469,
                        "y": 16.8
                      },
                      "opacity": 1,
                      "visible": true,
                      "children": [],
                      "fills": [
                        {
                          "type": "SOLID",
                          "color": {
                            "r": 1,
                            "g": 1,
                            "b": 1,
                            "a": 1
                          },
                          "opacity": 1
                        }
                      ],
                      "characters": "3.2 ETH",
                      "fontSize": 14,
                      "fontFamily": "Inter",
                      "textAlignHorizontal": "LEFT",
                      "fontWeight": 500,
                      "fontStyle": "Medium"
                    },
                    {
                      "type": "TEXT",
                      "name": "$12,305",
                      "size": {
                        "x": 45.130001068115234,
                        "y": 14.399999999999999
                      },
                      "opacity": 1,
                      "visible": true,
                      "children": [],
                      "fills": [
                        {
                          "type": "SOLID",
                          "color": {
                            "r": 0.44313725490196076,
                            "g": 0.44313725490196076,
                            "b": 0.47843137254901963,
                            "a": 1
                          },
                          "opacity": 1
                        }
                      ],
                      "characters": "$12,305",
                      "fontSize": 12,
                      "fontFamily": "Inter",
                      "textAlignHorizontal": "LEFT",
                      "fontWeight": 400,
                      "fontStyle": "Regular"
                    }
                  ],
                  "stackMode": "VERTICAL",
                  "itemSpacing": 2,
                  "paddingTop": 0,
                  "paddingRight": 24,
                  "paddingBottom": 0,
                  "paddingLeft": 24,
                  "primaryAxisAlignItems": "MIN",
                  "counterAxisAlignItems": "MAX"
                }
              ],
              "strokes": [
                {
                  "color": {
                    "r": 1,
                    "g": 1,
                    "b": 1,
                    "a": 0.06
                  },
                  "weight": 1,
                  "align": "INSIDE"
                }
              ],
              "stackMode": "HORIZONTAL",
              "itemSpacing": 0,
              "paddingTop": 14,
              "paddingRight": 16,
              "paddingBottom": 14,
              "paddingLeft": 16,
              "primaryAxisAlignItems": "MIN",
              "counterAxisAlignItems": "CENTER",
              "layoutSizingHorizontal": "FILL"
            },
            {
              "type": "FRAME",
              "name": "Coin: Solana",
              "size": {
                "x": 704,
                "y": 64
              },
              "opacity": 1,
              "visible": true,
              "children": [
                {
                  "type": "FRAME",
                  "name": "CoinInfo",
                  "size": {
                    "x": 520.7200012207031,
                    "y": 36
                  },
                  "opacity": 1,
                  "visible": true,
                  "children": [
                    {
                      "type": "ELLIPSE",
                      "name": "Icon:SOL",
                      "size": {
                        "x": 36,
                        "y": 36
                      },
                      "opacity": 1,
                      "visible": true,
                      "children": [],
                      "fills": [
                        {
                          "type": "SOLID",
                          "color": {
                            "r": 0.6,
                            "g": 0.27058823529411763,
                            "b": 1,
                            "a": 1
                          },
                          "opacity": 1
                        }
                      ]
                    },
                    {
                      "type": "FRAME",
                      "name": "CoinName",
                      "size": {
                        "x": 45.939998626708984,
                        "y": 33.2
                      },
                      "opacity": 1,
                      "visible": true,
                      "children": [
                        {
                          "type": "TEXT",
                          "name": "Solana",
                          "size": {
                            "x": 45.939998626708984,
                            "y": 16.8
                          },
                          "opacity": 1,
                          "visible": true,
                          "children": [],
                          "fills": [
                            {
                              "type": "SOLID",
                              "color": {
                                "r": 1,
                                "g": 1,
                                "b": 1,
                                "a": 1
                              },
                              "opacity": 1
                            }
                          ],
                          "characters": "Solana",
                          "fontSize": 14,
                          "fontFamily": "Inter",
                          "textAlignHorizontal": "LEFT",
                          "fontWeight": 600,
                          "fontStyle": "Semi Bold"
                        },
                        {
                          "type": "TEXT",
                          "name": "SOL",
                          "size": {
                            "x": 23.65999984741211,
                            "y": 14.399999999999999
                          },
                          "opacity": 1,
                          "visible": true,
                          "children": [],
                          "fills": [
                            {
                              "type": "SOLID",
                              "color": {
                                "r": 0.44313725490196076,
                                "g": 0.44313725490196076,
                                "b": 0.47843137254901963,
                                "a": 1
                              },
                              "opacity": 1
                            }
                          ],
                          "characters": "SOL",
                          "fontSize": 12,
                          "fontFamily": "Inter",
                          "textAlignHorizontal": "LEFT",
                          "fontWeight": 400,
                          "fontStyle": "Regular"
                        }
                      ],
                      "stackMode": "VERTICAL",
                      "itemSpacing": 2,
                      "paddingTop": 0,
                      "paddingRight": 0,
                      "paddingBottom": 0,
                      "paddingLeft": 0,
                      "primaryAxisAlignItems": "MIN",
                      "counterAxisAlignItems": "MIN"
                    }
                  ],
                  "stackMode": "HORIZONTAL",
                  "itemSpacing": 10,
                  "paddingTop": 0,
                  "paddingRight": 0,
                  "paddingBottom": 0,
                  "paddingLeft": 0,
                  "primaryAxisAlignItems": "MIN",
                  "counterAxisAlignItems": "CENTER",
                  "layoutSizingHorizontal": "FILL"
                },
                {
                  "type": "FRAME",
                  "name": "PriceCol",
                  "size": {
                    "x": 54.41999816894531,
                    "y": 33.2
                  },
                  "opacity": 1,
                  "visible": true,
                  "children": [
                    {
                      "type": "TEXT",
                      "name": "$142.80",
                      "size": {
                        "x": 54.41999816894531,
                        "y": 16.8
                      },
                      "opacity": 1,
                      "visible": true,
                      "children": [],
                      "fills": [
                        {
                          "type": "SOLID",
                          "color": {
                            "r": 1,
                            "g": 1,
                            "b": 1,
                            "a": 1
                          },
                          "opacity": 1
                        }
                      ],
                      "characters": "$142.80",
                      "fontSize": 14,
                      "fontFamily": "Inter",
                      "textAlignHorizontal": "LEFT",
                      "fontWeight": 500,
                      "fontStyle": "Medium"
                    },
                    {
                      "type": "TEXT",
                      "name": "-1.23%",
                      "size": {
                        "x": 41.650001525878906,
                        "y": 14.399999999999999
                      },
                      "opacity": 1,
                      "visible": true,
                      "children": [],
                      "fills": [
                        {
                          "type": "SOLID",
                          "color": {
                            "r": 0.9372549019607843,
                            "g": 0.26666666666666666,
                            "b": 0.26666666666666666,
                            "a": 1
                          },
                          "opacity": 1
                        }
                      ],
                      "characters": "-1.23%",
                      "fontSize": 12,
                      "fontFamily": "Inter",
                      "textAlignHorizontal": "LEFT",
                      "fontWeight": 600,
                      "fontStyle": "Semi Bold"
                    }
                  ],
                  "stackMode": "VERTICAL",
                  "itemSpacing": 2,
                  "paddingTop": 0,
                  "paddingRight": 0,
                  "paddingBottom": 0,
                  "paddingLeft": 0,
                  "primaryAxisAlignItems": "MIN",
                  "counterAxisAlignItems": "MAX"
                },
                {
                  "type": "FRAME",
                  "name": "HoldingCol",
                  "size": {
                    "x": 96.86000061035156,
                    "y": 33.2
                  },
                  "opacity": 1,
                  "visible": true,
                  "children": [
                    {
                      "type": "TEXT",
                      "name": "28 SOL",
                      "size": {
                        "x": 48.86000061035156,
                        "y": 16.8
                      },
                      "opacity": 1,
                      "visible": true,
                      "children": [],
                      "fills": [
                        {
                          "type": "SOLID",
                          "color": {
                            "r": 1,
                            "g": 1,
                            "b": 1,
                            "a": 1
                          },
                          "opacity": 1
                        }
                      ],
                      "characters": "28 SOL",
                      "fontSize": 14,
                      "fontFamily": "Inter",
                      "textAlignHorizontal": "LEFT",
                      "fontWeight": 500,
                      "fontStyle": "Medium"
                    },
                    {
                      "type": "TEXT",
                      "name": "$3,998",
                      "size": {
                        "x": 40.52000045776367,
                        "y": 14.399999999999999
                      },
                      "opacity": 1,
                      "visible": true,
                      "children": [],
                      "fills": [
                        {
                          "type": "SOLID",
                          "color": {
                            "r": 0.44313725490196076,
                            "g": 0.44313725490196076,
                            "b": 0.47843137254901963,
                            "a": 1
                          },
                          "opacity": 1
                        }
                      ],
                      "characters": "$3,998",
                      "fontSize": 12,
                      "fontFamily": "Inter",
                      "textAlignHorizontal": "LEFT",
                      "fontWeight": 400,
                      "fontStyle": "Regular"
                    }
                  ],
                  "stackMode": "VERTICAL",
                  "itemSpacing": 2,
                  "paddingTop": 0,
                  "paddingRight": 24,
                  "paddingBottom": 0,
                  "paddingLeft": 24,
                  "primaryAxisAlignItems": "MIN",
                  "counterAxisAlignItems": "MAX"
                }
              ],
              "strokes": [
                {
                  "color": {
                    "r": 1,
                    "g": 1,
                    "b": 1,
                    "a": 0.06
                  },
                  "weight": 1,
                  "align": "INSIDE"
                }
              ],
              "stackMode": "HORIZONTAL",
              "itemSpacing": 0,
              "paddingTop": 14,
              "paddingRight": 16,
              "paddingBottom": 14,
              "paddingLeft": 16,
              "primaryAxisAlignItems": "MIN",
              "counterAxisAlignItems": "CENTER",
              "layoutSizingHorizontal": "FILL"
            },
            {
              "type": "FRAME",
              "name": "Coin: Cardano",
              "size": {
                "x": 704,
                "y": 64
              },
              "opacity": 1,
              "visible": true,
              "children": [
                {
                  "type": "FRAME",
                  "name": "CoinInfo",
                  "size": {
                    "x": 508.36999893188477,
                    "y": 36
                  },
                  "opacity": 1,
                  "visible": true,
                  "children": [
                    {
                      "type": "ELLIPSE",
                      "name": "Icon:ADA",
                      "size": {
                        "x": 36,
                        "y": 36
                      },
                      "opacity": 1,
                      "visible": true,
                      "children": [],
                      "fills": [
                        {
                          "type": "SOLID",
                          "color": {
                            "r": 0,
                            "g": 0.2,
                            "b": 0.6784313725490196,
                            "a": 1
                          },
                          "opacity": 1
                        }
                      ]
                    },
                    {
                      "type": "FRAME",
                      "name": "CoinName",
                      "size": {
                        "x": 57.470001220703125,
                        "y": 33.2
                      },
                      "opacity": 1,
                      "visible": true,
                      "children": [
                        {
                          "type": "TEXT",
                          "name": "Cardano",
                          "size": {
                            "x": 57.470001220703125,
                            "y": 16.8
                          },
                          "opacity": 1,
                          "visible": true,
                          "children": [],
                          "fills": [
                            {
                              "type": "SOLID",
                              "color": {
                                "r": 1,
                                "g": 1,
                                "b": 1,
                                "a": 1
                              },
                              "opacity": 1
                            }
                          ],
                          "characters": "Cardano",
                          "fontSize": 14,
                          "fontFamily": "Inter",
                          "textAlignHorizontal": "LEFT",
                          "fontWeight": 600,
                          "fontStyle": "Semi Bold"
                        },
                        {
                          "type": "TEXT",
                          "name": "ADA",
                          "size": {
                            "x": 24.809999465942383,
                            "y": 14.399999999999999
                          },
                          "opacity": 1,
                          "visible": true,
                          "children": [],
                          "fills": [
                            {
                              "type": "SOLID",
                              "color": {
                                "r": 0.44313725490196076,
                                "g": 0.44313725490196076,
                                "b": 0.47843137254901963,
                                "a": 1
                              },
                              "opacity": 1
                            }
                          ],
                          "characters": "ADA",
                          "fontSize": 12,
                          "fontFamily": "Inter",
                          "textAlignHorizontal": "LEFT",
                          "fontWeight": 400,
                          "fontStyle": "Regular"
                        }
                      ],
                      "stackMode": "VERTICAL",
                      "itemSpacing": 2,
                      "paddingTop": 0,
                      "paddingRight": 0,
                      "paddingBottom": 0,
                      "paddingLeft": 0,
                      "primaryAxisAlignItems": "MIN",
                      "counterAxisAlignItems": "MIN"
                    }
                  ],
                  "stackMode": "HORIZONTAL",
                  "itemSpacing": 10,
                  "paddingTop": 0,
                  "paddingRight": 0,
                  "paddingBottom": 0,
                  "paddingLeft": 0,
                  "primaryAxisAlignItems": "MIN",
                  "counterAxisAlignItems": "CENTER",
                  "layoutSizingHorizontal": "FILL"
                },
                {
                  "type": "FRAME",
                  "name": "PriceCol",
                  "size": {
                    "x": 42.47999954223633,
                    "y": 33.2
                  },
                  "opacity": 1,
                  "visible": true,
                  "children": [
                    {
                      "type": "TEXT",
                      "name": "$0.82",
                      "size": {
                        "x": 39.04999923706055,
                        "y": 16.8
                      },
                      "opacity": 1,
                      "visible": true,
                      "children": [],
                      "fills": [
                        {
                          "type": "SOLID",
                          "color": {
                            "r": 1,
                            "g": 1,
                            "b": 1,
                            "a": 1
                          },
                          "opacity": 1
                        }
                      ],
                      "characters": "$0.82",
                      "fontSize": 14,
                      "fontFamily": "Inter",
                      "textAlignHorizontal": "LEFT",
                      "fontWeight": 500,
                      "fontStyle": "Medium"
                    },
                    {
                      "type": "TEXT",
                      "name": "+2.15%",
                      "size": {
                        "x": 42.47999954223633,
                        "y": 14.399999999999999
                      },
                      "opacity": 1,
                      "visible": true,
                      "children": [],
                      "fills": [
                        {
                          "type": "SOLID",
                          "color": {
                            "r": 0.13333333333333333,
                            "g": 0.7725490196078432,
                            "b": 0.3686274509803922,
                            "a": 1
                          },
                          "opacity": 1
                        }
                      ],
                      "characters": "+2.15%",
                      "fontSize": 12,
                      "fontFamily": "Inter",
                      "textAlignHorizontal": "LEFT",
                      "fontWeight": 600,
                      "fontStyle": "Semi Bold"
                    }
                  ],
                  "stackMode": "VERTICAL",
                  "itemSpacing": 2,
                  "paddingTop": 0,
                  "paddingRight": 0,
                  "paddingBottom": 0,
                  "paddingLeft": 0,
                  "primaryAxisAlignItems": "MIN",
                  "counterAxisAlignItems": "MAX"
                },
                {
                  "type": "FRAME",
                  "name": "HoldingCol",
                  "size": {
                    "x": 121.1500015258789,
                    "y": 33.2
                  },
                  "opacity": 1,
                  "visible": true,
                  "children": [
                    {
                      "type": "TEXT",
                      "name": "3,400 ADA",
                      "size": {
                        "x": 73.1500015258789,
                        "y": 16.8
                      },
                      "opacity": 1,
                      "visible": true,
                      "children": [],
                      "fills": [
                        {
                          "type": "SOLID",
                          "color": {
                            "r": 1,
                            "g": 1,
                            "b": 1,
                            "a": 1
                          },
                          "opacity": 1
                        }
                      ],
                      "characters": "3,400 ADA",
                      "fontSize": 14,
                      "fontFamily": "Inter",
                      "textAlignHorizontal": "LEFT",
                      "fontWeight": 500,
                      "fontStyle": "Medium"
                    },
                    {
                      "type": "TEXT",
                      "name": "$2,788",
                      "size": {
                        "x": 39.77000045776367,
                        "y": 14.399999999999999
                      },
                      "opacity": 1,
                      "visible": true,
                      "children": [],
                      "fills": [
                        {
                          "type": "SOLID",
                          "color": {
                            "r": 0.44313725490196076,
                            "g": 0.44313725490196076,
                            "b": 0.47843137254901963,
                            "a": 1
                          },
                          "opacity": 1
                        }
                      ],
                      "characters": "$2,788",
                      "fontSize": 12,
                      "fontFamily": "Inter",
                      "textAlignHorizontal": "LEFT",
                      "fontWeight": 400,
                      "fontStyle": "Regular"
                    }
                  ],
                  "stackMode": "VERTICAL",
                  "itemSpacing": 2,
                  "paddingTop": 0,
                  "paddingRight": 24,
                  "paddingBottom": 0,
                  "paddingLeft": 24,
                  "primaryAxisAlignItems": "MIN",
                  "counterAxisAlignItems": "MAX"
                }
              ],
              "strokes": [
                {
                  "color": {
                    "r": 1,
                    "g": 1,
                    "b": 1,
                    "a": 0.06
                  },
                  "weight": 1,
                  "align": "INSIDE"
                }
              ],
              "stackMode": "HORIZONTAL",
              "itemSpacing": 0,
              "paddingTop": 14,
              "paddingRight": 16,
              "paddingBottom": 14,
              "paddingLeft": 16,
              "primaryAxisAlignItems": "MIN",
              "counterAxisAlignItems": "CENTER",
              "layoutSizingHorizontal": "FILL"
            }
          ],
          "stackMode": "VERTICAL",
          "itemSpacing": 0,
          "paddingTop": 16,
          "paddingRight": 8,
          "paddingBottom": 16,
          "paddingLeft": 8,
          "primaryAxisAlignItems": "MIN",
          "counterAxisAlignItems": "MIN",
          "layoutSizingHorizontal": "FILL"
        }
      ],
      "fills": [
        {
          "type": "SOLID",
          "color": {
            "r": 0.0392156862745098,
            "g": 0.0392156862745098,
            "b": 0.0392156862745098,
            "a": 1
          },
          "opacity": 1
        }
      ],
      "stackMode": "VERTICAL",
      "itemSpacing": 0,
      "paddingTop": 0,
      "paddingRight": 0,
      "paddingBottom": 0,
      "paddingLeft": 0,
      "primaryAxisAlignItems": "MIN",
      "counterAxisAlignItems": "MIN",
      "layoutSizingHorizontal": "FIXED"
    }
  ]
}